NayanGeneralUtils/__init__.py
NayanGeneralUtils/bibtexHandler.py
NayanGeneralUtils/equationHandler.py
NayanGeneralUtils/fileHandling.py
NayanGeneralUtils/inputOutput.py
NayanGeneralUtils/misc.py
NayanGeneralUtils/plotting.py
NayanGeneralUtils/progress.py
nayangeneralutils-1.6.dist-info/.DS_Store
nayangeneralutils-1.6.dist-info/METADATA
nayangeneralutils-1.6.dist-info/WHEEL
nayangeneralutils-1.6.dist-info/top_level.txt
nayangeneralutils-1.6.dist-info/RECORD
