Metadata-Version: 2.4
Name: NayanGeneralUtils
Version: 1.6
Summary: A personal library of generally useful functions, methods and classes
Home-page: https://github.com/NayanDusoruth/NayanGeneralUtils
Author: Nayan Dusoruth
Author-email: nayan.dusoruth@gmail.com
License: MIT
Classifier: Programming Language :: Python :: 3
Classifier: License :: OSI Approved :: MIT License
Classifier: Operating System :: OS Independent
Requires-Dist: contourpy==1.3.3
Requires-Dist: cycler==0.12.1
Requires-Dist: fonttools==4.59.2
Requires-Dist: kiwisolver==1.4.9
Requires-Dist: matplotlib==3.10.5
Requires-Dist: mpmath==1.3.0
Requires-Dist: numpy==2.0
Requires-Dist: packaging==25.0
Requires-Dist: pandas==2.3.2
Requires-Dist: pillow==11.3.0
Requires-Dist: pyparsing==3.2.3
Requires-Dist: python-dateutil==2.9.0.post0
Requires-Dist: pytz==2025.2
Requires-Dist: scipy==1.16.1
Requires-Dist: six==1.17.0
Requires-Dist: sympy==1.14.0
Requires-Dist: tzdata==2025.2
Dynamic: author
Dynamic: classifier
Dynamic: description
Dynamic: description-content-type
Dynamic: home-page
Dynamic: license
Dynamic: requires-dist
Dynamic: summary
